oxidasim-0.1.0.dist-info/METADATA
oxidasim-0.1.0.dist-info/WHEEL
oxidasim-0.1.0.dist-info/licenses/LICENSE-APACHE
oxidasim-0.1.0.dist-info/licenses/LICENSE-MIT
oxidasim/sampling/__init__.py
oxidasim/_rs/sampling/__init__.pyi
oxidasim/_rs/__init__.pyi
oxidasim/__init__.py
oxidasim/py.typed
oxidasim/_rs.abi3.so
oxidasim-0.1.0.dist-info/RECORD
