Metadata-Version: 2.4
Name: oxidasim
Version: 0.1.0
Classifier: Programming Language :: Python
Classifier: Programming Language :: Rust
Classifier: License :: OSI Approved :: MIT License
Classifier: License :: OSI Approved :: Apache Software License
Classifier: Topic :: Games/Entertainment :: Simulation
Requires-Dist: oxidasim[dev] ; extra == 'all'
Requires-Dist: oxidasim[test] ; extra == 'dev'
Requires-Dist: pytest ~=8.0 ; extra == 'test'
Provides-Extra: all
Provides-Extra: dev
Provides-Extra: test
License-File: LICENSE-APACHE
License-File: LICENSE-MIT
Summary: Utilities for simulations
Keywords: simulation,robotics
Home-Page: https://github.com/AndrejOrsula/oxidasim
Author-email: Andrej Orsula <orsula.andrej@gmail.com>
Maintainer-email: Andrej Orsula <orsula.andrej@gmail.com>
License: MIT OR Apache-2.0
Requires-Python: >=3.10
Project-URL: Repository, https://github.com/AndrejOrsula/oxidasim
